rocketapi
