Metadata-Version: 2.1
Name: rocketapi
Version: 1.0.12
Summary: RocketAPI Python SDK
Home-page: https://github.com/rocketapi-io/rocketapi-python
Download-URL: https://github.com/rocketapi-io/rocketapi-python/archive/refs/tags/v1.0.12.tar.gz
Author: RocketAPI
Author-email: developer@rocketapi.io
